setup.cfg
setup.py
game_ui/FOR_TESTS.py
game_ui/__init__.py
game_ui/button.py
game_ui/input.py
game_ui.egg-info/PKG-INFO
game_ui.egg-info/SOURCES.txt
game_ui.egg-info/dependency_links.txt
game_ui.egg-info/top_level.txt